README.md
setup.py
danger/__init__.py
danger/date.py
danger/file.py
danger/log.py
danger/md5.py
danger/mysql.py
danger/ssh.py
danger/aliyun/__init__.py
danger/aliyun/datahub.py
danger/aliyun/loghub.py
danger_util.egg-info/PKG-INFO
danger_util.egg-info/SOURCES.txt
danger_util.egg-info/dependency_links.txt
danger_util.egg-info/requires.txt
danger_util.egg-info/top_level.txt