Metadata-Version: 2.1
Name: danger-util
Version: 0.0.1
Summary: A python tool package
Home-page: https://github.com/danger812/danger
Author: wushiyong
Author-email: wushiyong1209@gmail.com
License: UNKNOWN
Platform: UNKNOWN
Classifier: Programming Language :: Python :: 3
Classifier: License :: OSI Approved :: Apache Software License
Classifier: Operating System :: OS Independent
